readPdfFiles/__init__.py
readPdfFiles/readPdfWithFitz.py
readPdfFiles/readPdfWithPdfminer.py
readPdfFiles/readPdfWithPyPDF2.py
readPdfFiles/readPdfWithTabula.py
ReadPdfFiles-1.0.5.dist-info/METADATA
ReadPdfFiles-1.0.5.dist-info/WHEEL
ReadPdfFiles-1.0.5.dist-info/top_level.txt
ReadPdfFiles-1.0.5.dist-info/RECORD
