Metadata-Version: 2.1
Name: ReadPdfFiles
Version: 1.0.5
Summary: A Python package for reading PDF files.
Author: Jayesh Vani
Author-email: jayeshvani2@gmail.com
Classifier: Programming Language :: Python :: 3
Classifier: License :: OSI Approved :: MIT License
Classifier: Operating System :: OS Independent
Requires-Dist: PyMuPDF
Requires-Dist: PyPDF2
Requires-Dist: tabula-py
Requires-Dist: pdfminer.six
